lyydata
