Metadata-Version: 2.1
Name: lyydata
Version: 1.7
Summary: lyydata for lyy
Author: yy
Author-email: 
License: MIT
License-File: LICENSE
